DisOAuth/__init__.py
DisOAuth/__main__.py
DisOAuth/__version__.py
DisOAuth/common.py
DisOAuth/exceptions.py
DisOAuth/models.py
DisOAuth/url.py
DisOAuth/deprecated/common.py
DisOAuth/deprecated/models.py
DisOAuth/deprecated/url.py
Async_DisOAuth-2.0.1.dist-info/LICENSE
Async_DisOAuth-2.0.1.dist-info/METADATA
Async_DisOAuth-2.0.1.dist-info/WHEEL
Async_DisOAuth-2.0.1.dist-info/entry_points.txt
Async_DisOAuth-2.0.1.dist-info/top_level.txt
Async_DisOAuth-2.0.1.dist-info/RECORD
