Metadata-Version: 2.1
Name: Async-DisOAuth
Version: 2.0.1
Summary: Works with Discord API, to get 
Author: Arcader717
License: MIT License
Project-URL: Homepage, https://github.com/disoauth/DiscoAuth
Project-URL: Bug Tracker, https://github.com/disoauth/DiscoAuth/issues
Project-URL: Repository, https://github.com/disoauth/DiscoAuth
Project-URL: Documentation, https://async-disoauth2.readthedocs.io/en/latest/index.html
Project-URL: Changelog, https://github.com/disoauth/DiscoAuth/docs/CHANGELOG.rst
Keywords: Discord,OAuth2,oauth,auth,async
Classifier: Intended Audience :: Developers
Classifier: License :: OSI Approved :: MIT License
Classifier: Natural Language :: English
Classifier: Operating System :: OS Independent
Classifier: Topic :: Other/Nonlisted Topic
Classifier: Programming Language :: Python
Requires-Python: >=3.7
License-File: LICENSE
Requires-Dist: requests
Requires-Dist: click
